indico_search/__init__.py
indico_search/base.py
indico_search/blueprint.py
indico_search/controllers.py
indico_search/forms.py
indico_search/plugin.py
indico_search/util.py
indico_search/views.py
indico_search/static/dist/manifest.json
indico_search/static/dist/css/main.ab8ca02e.css
indico_search/static/dist/css/main.ab8ca02e.css.map
indico_search/static/dist/js/main.a637af60.bundle.js
indico_search/static/dist/js/main.a637af60.bundle.js.map
indico_search/templates/results.html
indico_search/templates/searchbox_category.html
indico_search/templates/searchbox_conference.html
indico_search/translations/messages-js.pot
indico_search/translations/messages.pot
indico_search/translations/fr_FR/LC_MESSAGES/messages-js.po
indico_search/translations/fr_FR/LC_MESSAGES/messages.mo
indico_search/translations/fr_FR/LC_MESSAGES/messages.po
indico_plugin_search-2.3.dist-info/METADATA
indico_plugin_search-2.3.dist-info/WHEEL
indico_plugin_search-2.3.dist-info/entry_points.txt
indico_plugin_search-2.3.dist-info/top_level.txt
indico_plugin_search-2.3.dist-info/RECORD
